azsctl-0.2.6.data/scripts/azsctl
azsctl-0.2.6.data/scripts/azsctl.completion.sh
azsctl-0.2.6.dist-info/DESCRIPTION.rst
azsctl-0.2.6.dist-info/METADATA
azsctl-0.2.6.dist-info/RECORD
azsctl-0.2.6.dist-info/WHEEL
azsctl-0.2.6.dist-info/metadata.json
azsctl-0.2.6.dist-info/top_level.txt
azsentinel/__init__.py
azsentinel/__main__.py
azsentinel/api.py
azsentinel/auth.py
azsentinel/classes.py
azsentinel/config.py
azsentinel/commands/__init__.py
azsentinel/commands/alert.py
azsentinel/commands/analytics.py
azsentinel/commands/dataconnector.py
azsentinel/commands/incident.py
azsentinel/commands/rule.py
azsentinel/commands/workspace.py
azsentinel/ui/__init__.py
azsentinel/ui/azsctlui.py
azsentinel/ui/controller.py
azsentinel/ui/signals.py
azsentinel/ui/statusbar.py
azsentinel/ui/window.py
azsentinel/ui/widget/__init__.py
azsentinel/ui/widget/dialog.py
azsentinel/ui/widget/incident.py
azsentinel/ui/widget/list.py
azsentinel/ui/widget/rule.py
azsentinel/ui/widget/table.py
azsentinel/ui/widget/tabs.py
azsentinel/validators/__init__.py
azsentinel/validators/scheduled_rule.py
tests/__init__.py
tests/test_rule.py
